{
  "categories": [
    {
      "id": "enter",
      "nameCN": "进站",
      "nameEN": "ENTER",
      "bgColor": "#ffffff",
      "color": "#000000"
    },
    {
      "id": "exit",
      "nameCN": "出站",
      "nameEN": "EXIT",
      "bgColor": "#FFD701",
      "color": "#000000"
    },
    {
      "id": "facility",
      "nameCN": "设施",
      "nameEN": "FACILITY",
      "bgColor": "#333F48",
      "color": "#ffffff"
    },
    {
      "id": "misc",
      "nameCN": "其他",
      "nameEN": "MISC"
    }
  ],
  "lines": [
    {
      "id": "L1",
      "number": "1",
      "nameCN": "号线",
      "nameEN": "Line 1",
      "color": "#E60012"
    },
    {
      "id": "L2",
      "number": "2",
      "nameCN": "号线",
      "nameEN": "Line 2",
      "color": "#009E52"
    },
    {
      "id": "L3",
      "number": "3",
      "nameCN": "号线",
      "nameEN": "Line 3",
      "color": "#FFD700"
    },
    {
      "id": "L4",
      "number": "4",
      "nameCN": "号线",
      "nameEN": "Line 4",
      "color": "#0054A6"
    }
  ],
  "components": [
    {
      "id": "arrow",
      "name": "箭头",
      "description": "",
      "category": "enter",
      "feature": "selectIcon",
      "type": "composite",
      "useList": true,
      "iconNames": [
        "上",
        "下",
        "左",
        "右",
        "左上",
        "右上",
        "左下",
        "右下",
        "前方向左",
        "前方向右",
        "左行向下",
        "右行向下"
      ],
      "iconFiles": [
        "icon/arrows/up.svg",
        "icon/arrows/down.svg",
        "icon/arrows/left.svg",
        "icon/arrows/right.svg",
        "icon/arrows/leftup.svg",
        "icon/arrows/rightup.svg",
        "icon/arrows/leftdown.svg",
        "icon/arrows/rightdown.svg",
        "icon/arrows/upleft.svg",
        "icon/arrows/upright.svg",
        "icon/arrows/downleft.svg",
        "icon/arrows/downright.svg"
      ],
      "ingredients": [
        {
          "componentId": "icon",
          "props": {
            "src": "icon/arrows/up.svg"
          }
        }
      ]
    },
    {
      "id": "trainIcon",
      "name": "制式标志",
      "description": "",
      "category": "enter",
      "feature": "selectIcon",
      "type": "composite",
      "useList":true,
      "iconNames":["单轨","地铁"],
      "iconFiles": [
        "icon/monorail.svg",
        "icon/metro.svg"
      ],
      "ingredients": [
        {
          "componentId": "icon",
          "props": {
            "src": "icon/monorail.svg"
          }
        }
      ]
    },
    {
      "id": "rideIcon",
      "name": "乘车标志",
      "description": "",
      "category": "enter",
      "feature": "selectIcon",
      "useList": true,
      "type": "composite",
      "iconNames":["乘车"],
      "iconFiles": [
        "icon/train.svg"
      ],
      "ingredients": [
        {
          "componentId": "icon",
          "props": {
            "src": "icon/train.svg"
          }
        }
      ]
    },
    {
      "id": "lineNumber",
      "name": "线路号",
      "description": "",
      "category": "enter",
      "feature": "selectLine editText",
      "type": "composite",
      "colorBarAdjustment": true,
      "ingredients": [
        {
          "componentId": "colorBar",
          "props": {
            "color": "#b0b0b0"
          }
        },
        {
          "componentId": "largeText",
          "props": {
            "text": "0"
          }
        },
        {
          "componentId": "textBox",
          "props": {
            "textCN": "号线",
            "textEN": "Line 0"
          }
        }
      ]
    },
    {
      "id": "lineNumberText",
      "name": "线路号",
      "description": "文字线路",
      "category": "enter",
      "feature": "selectLine editText",
      "type": "composite",
      "colorBarAdjustment": true,
      "ingredients": [
        {
          "componentId": "colorBar",
          "props": {
            "color": "#b0b0b0"
          }
        },
        {
          "componentId": "textBox",
          "props": {
            "textCN": "东铁线",
            "textEN": "East Rail Line"
          }
        }
      ]
    },
    {
      "id": "entranceNumber",
      "name": "出入口号",
      "description": "",
      "category": "enter",
      "feature": "editText",
      "type": "composite",
      "invertOrder": true,
      "ingredients": [
        {
          "componentId": "largeText",
          "props": {
            "text": "0"
          }
        },
        {
          "componentId": "textBox",
          "props": {
            "textCN": "出入口",
            "textEN": "Entrance"
          }
        }
      ]
    },
    {
      "id": "stationName",
      "name": "车站名",
      "description": "",
      "category": "enter",
      "feature": "editText",
      "type": "composite",
      "ingredients": [
        {
          "componentId": "textBox",
          "props": {
            "textCN": "金钟",
            "textEN": "Admiralty",
            "textCNStyle": "font-weight:700;text-align:center",
            "textENStyle": "font-weight:700;text-align:center"
          }
        }
      ]
    },
    {
      "id": "lineColorText",
      "name": "线路色文字",
      "description": "",
      "thumbnailBg": "dark",
      "category": "misc",
      "feature": "editText",
      "type": "composite",
      "ingredients": [
        {
          "componentId": "textBox",
          "props": {
            "textCN": "方向",
            "textEN": "To"
          }
        }
      ]
    }
  ]
}